topsis/102203527.py
topsis/__init__.py
Topsis_Akshita_102203527-0.1.0.dist-info/LICENSE
Topsis_Akshita_102203527-0.1.0.dist-info/METADATA
Topsis_Akshita_102203527-0.1.0.dist-info/WHEEL
Topsis_Akshita_102203527-0.1.0.dist-info/top_level.txt
Topsis_Akshita_102203527-0.1.0.dist-info/RECORD
