Metadata-Version: 2.1
Name: Topsis-Akshita-102203527
Version: 0.1.0
Summary: A Python package for implementing the TOPSIS method.
Home-page: https://github.com/Akshita1414/Topsis-Akshita-102203527.git
Author: Akshita
Author-email: akshita.chauhan1414@gmail.com
Classifier: Programming Language :: Python :: 3
Classifier: License :: OSI Approved :: MIT License
Classifier: Operating System :: OS Independent
Requires-Python: >=3.6
License-File: LICENSE
Requires-Dist: numpy
Requires-Dist: pandas
